<?xml version="1.0" encoding="UTF-8"?>
<!DOCTYPE rules SYSTEM "https://resources.jetbrains.com/writerside/1.0/redirection-rules.dtd">
<rules>
    <!-- format is as follows
    <rule id="<unique id>">
        <accepts>page.html</accepts>
    </rule>
    -->
	<rule id="34d72c89">
		<description>Created after removal of "None" from plat</description>
		<accepts>None.html</accepts>
	</rule>
    <rule id="4000f99e">
        <description>Created after removal of "Topic title" from plat</description>
        <accepts>Getting-Started.html</accepts>
    </rule>
</rules>